{"widths":{"0":16,"1":16,"2":16,"3":16,"4":16,"5":16,"6":16,"7":16,"8":16,"9":16,"`":9,"-":10,"=":16,"~":17,"!":8,"@":28,"#":17,"$":17,"%":25,"^":14,"&":20,"*":12,"(":11,")":9,"_":17,"+":16,"q":16,"w":22,"e":16,"r":10,"t":9,"y":15,"u":16,"i":6,"o":16,"p":16,"[":9,"]":8,"a":17,"s":14,"d":16,"f":9,"g":16,"h":16,"j":6,"k":16,"l":6,"'":5,"\\":9,"z":14,"x":15,"c":15,"v":15,"b":16,"n":16,"m":23,",":8,".":8,"/":9,"Q":22,"W":28,"E":19,"R":20,"T":18,"Y":20,"U":20,"I":8,"O":22,"P":19,"{":10,"}":10,"A":20,"S":19,"D":20,"F":17,"G":22,"H":20,"J":14,"K":20,"L":16,":":8,"Z":18,"X":20,"C":21,"V":20,"B":19,"N":20,"M":23,"<":16,">":16,"?":16,"|":7,"Й":20,"Ц":22,"У":19,"К":18,"Е":19,"Н":20,"Г":16,"Ш":26,"Щ":27,"З":17,"Х":20,"Ъ":22,"Ф":21,"Ы":25,"В":19,"А":20,"П":20,"Р":19,"О":22,"Л":18,"Д":20,"Ж":27,"Э":21,"Я":20,"Ч":19,"С":21,"М":23,"И":20,"Т":18,"Ь":18,"Б":18,"Ю":28,"й":16,"ц":17,"у":15,"к":14,"е":16,"н":15,"г":11,"ш":22,"щ":24,"з":13,"х":15,"ъ":18,"ф":23,"ы":20,"в":15,"а":17,"п":15,"р":16,"о":16,"л":16,"д":17,"ж":20,"э":15,"я":15,"ч":15,"с":15,"м":19,"и":16,"т":14,"ь":15,"б":16,"ю":21,"\"":10,"№":30,";":8},"height":32}