{"widths":{"0":10,"1":5,"2":8,"3":8,"4":9,"5":8,"6":9,"7":9,"8":10,"9":9,"`":4,"-":7,"=":8,"~":8,"!":4,"@":11,"#":9,"$":8,"%":12,"^":8,"&":11,"*":7,"(":5,")":5,"_":8,"+":8,"q":8,"w":11,"e":8,"r":8,"t":7,"y":8,"u":8,"i":4,"o":8,"p":8,"[":5,"]":5,"a":8,"s":6,"d":8,"f":8,"g":8,"h":8,"j":5,"k":8,"l":5,"'":3,"\\":6,"z":8,"x":8,"c":7,"v":8,"b":8,"n":8,"m":10,",":4,".":4,"/":7,"Q":9,"W":10,"E":8,"R":9,"T":8,"Y":8,"U":9,"I":7,"O":8,"P":8,"{":6,"}":5,"A":9,"S":6,"D":9,"F":7,"G":9,"H":8,"J":7,"K":9,"L":8,":":4,"Z":8,"X":9,"C":8,"V":8,"B":8,"N":10,"M":11,"<":6,">":6,"?":8,"|":4,"Й":8,"Ц":8,"У":8,"К":8,"Е":8,"Н":8,"Г":8,"Ш":8,"Щ":8,"З":8,"Х":8,"Ъ":8,"Ф":8,"Ы":8,"В":8,"А":8,"П":8,"Р":8,"О":8,"Л":8,"Д":8,"Ж":8,"Э":8,"Я":8,"Ч":8,"С":8,"М":8,"И":8,"Т":8,"Ь":8,"Б":8,"Ю":8,"й":8,"ц":8,"у":8,"к":8,"е":8,"н":8,"г":8,"ш":8,"щ":8,"з":8,"х":8,"ъ":8,"ф":8,"ы":8,"в":8,"а":8,"п":8,"р":8,"о":8,"л":8,"д":8,"ж":8,"э":8,"я":8,"ч":8,"с":8,"м":8,"и":8,"т":8,"ь":8,"б":8,"ю":8,"\"":5,"№":8,";":4},"height":19}