{"widths":{"0":31,"1":31,"2":31,"3":31,"4":31,"5":31,"6":31,"7":31,"8":31,"9":31,"`":19,"-":19,"=":33,"~":33,"!":16,"@":57,"#":32,"$":32,"%":50,"^":27,"&":38,"*":22,"(":20,")":19,"_":33,"+":33,"q":31,"w":42,"e":31,"r":19,"t":17,"y":29,"u":31,"i":12,"o":31,"p":31,"[":17,"]":16,"a":33,"s":28,"d":31,"f":17,"g":31,"h":31,"j":12,"k":30,"l":12,"'":11,"\\":17,"z":28,"x":29,"c":28,"v":29,"b":31,"n":31,"m":47,",":16,".":16,"/":17,"Q":44,"W":54,"E":37,"R":40,"T":34,"Y":38,"U":40,"I":16,"O":44,"P":37,"{":19,"}":19,"A":39,"S":37,"D":40,"F":34,"G":44,"H":40,"J":28,"K":38,"L":31,":":16,"Z":34,"X":38,"C":40,"V":39,"B":37,"N":40,"M":47,"<":33,">":33,"?":31,"|":15,"Й":40,"Ц":42,"У":37,"К":34,"Е":37,"Н":40,"Г":31,"Ш":51,"Щ":53,"З":34,"Х":38,"Ъ":44,"Ф":43,"Ы":50,"В":37,"А":39,"П":40,"Р":37,"О":44,"Л":37,"Д":38,"Ж":52,"Э":40,"Я":40,"Ч":37,"С":40,"М":47,"И":40,"Т":34,"Ь":37,"Б":37,"Ю":57,"й":31,"ц":32,"у":29,"к":26,"е":31,"н":31,"г":20,"ш":45,"щ":46,"з":26,"х":29,"ъ":35,"ф":46,"ы":40,"в":30,"а":33,"п":30,"р":31,"о":31,"л":33,"д":33,"ж":39,"э":29,"я":30,"ч":29,"с":28,"м":39,"и":31,"т":26,"ь":29,"б":32,"ю":42,"\"":20,"№":60,";":16},"height":64}