{"widths":{"0":58,"1":58,"2":58,"3":58,"4":58,"5":58,"6":58,"7":58,"8":58,"9":58,"`":40,"-":33,"=":58,"~":58,"!":32,"@":98,"#":68,"$":58,"%":91,"^":58,"&":69,"*":49,"(":35,")":35,"_":51,"+":58,"q":61,"w":79,"e":58,"r":41,"t":43,"y":53,"u":59,"i":29,"o":61,"p":61,"[":36,"]":36,"a":54,"s":47,"d":61,"f":43,"g":60,"h":59,"j":29,"k":56,"l":31,"'":27,"\\":46,"z":49,"x":54,"c":48,"v":54,"b":61,"n":60,"m":88,",":28,".":28,"/":45,"Q":79,"W":95,"E":60,"R":65,"T":59,"Y":64,"U":71,"I":30,"O":79,"P":63,"{":36,"}":36,"A":69,"S":55,"D":74,"F":56,"G":69,"H":73,"J":52,"K":66,"L":54,":":28,"Z":60,"X":67,"C":65,"V":69,"B":67,"N":75,"M":89,"<":58,">":58,"?":43,"|":31,"Й":75,"Ц":76,"У":63,"К":66,"Е":60,"Н":73,"Г":55,"Ш":101,"Щ":105,"З":60,"Х":67,"Ъ":75,"Ф":88,"Ы":90,"В":67,"А":69,"П":72,"Р":63,"О":79,"Л":75,"Д":78,"Ж":96,"Э":64,"Я":67,"Ч":67,"С":65,"М":89,"И":75,"Т":59,"Ь":64,"Б":64,"Ю":107,"й":62,"ц":62,"у":53,"к":57,"е":58,"н":60,"г":45,"ш":86,"щ":88,"з":51,"х":54,"ъ":63,"ф":79,"ы":80,"в":58,"а":54,"п":60,"р":61,"о":61,"л":62,"д":64,"ж":81,"э":52,"я":58,"ч":56,"с":48,"м":76,"и":62,"т":49,"ь":56,"б":61,"ю":85,"\"":47,"№":116,";":27},"height":113}