{"widths":{"0":65,"1":65,"2":65,"3":65,"4":65,"5":65,"6":65,"7":65,"8":65,"9":65,"`":65,"-":65,"=":65,"~":65,"!":65,"@":65,"#":65,"$":65,"%":65,"^":65,"&":65,"*":65,"(":65,")":65,"_":65,"+":65,"q":65,"w":65,"e":65,"r":65,"t":65,"y":65,"u":65,"i":65,"o":65,"p":65,"[":65,"]":65,"a":65,"s":65,"d":65,"f":65,"g":65,"h":65,"j":65,"k":65,"l":65,"'":65,"\\":65,"z":65,"x":65,"c":65,"v":65,"b":65,"n":65,"m":65,",":65,".":65,"/":65,"Q":65,"W":65,"E":65,"R":65,"T":65,"Y":65,"U":65,"I":65,"O":65,"P":65,"{":65,"}":65,"A":65,"S":65,"D":65,"F":65,"G":65,"H":65,"J":65,"K":65,"L":65,":":65,"Z":65,"X":65,"C":65,"V":65,"B":65,"N":65,"M":65,"<":65,">":65,"?":65,"|":65,"Й":65,"Ц":65,"У":65,"К":65,"Е":65,"Н":65,"Г":65,"Ш":65,"Щ":65,"З":65,"Х":65,"Ъ":65,"Ф":65,"Ы":65,"В":65,"А":65,"П":65,"Р":65,"О":65,"Л":65,"Д":65,"Ж":65,"Э":65,"Я":65,"Ч":65,"С":65,"М":65,"И":65,"Т":65,"Ь":65,"Б":65,"Ю":65,"й":65,"ц":65,"у":65,"к":65,"е":65,"н":65,"г":65,"ш":65,"щ":65,"з":65,"х":65,"ъ":65,"ф":65,"ы":65,"в":65,"а":65,"п":65,"р":65,"о":65,"л":65,"д":65,"ж":65,"э":65,"я":65,"ч":65,"с":65,"м":65,"и":65,"т":65,"ь":65,"б":65,"ю":65,"\"":65,"№":65,";":65},"height":118}